robustlink/__init__.py
robustlink/__main__.py
robustlink/_init_plots.py
robustlink/analysis.py
robustlink/correlate_metacells_atac_rna.py
robustlink/correlate_metacells_mc_rna.py
robustlink/enhancer_gene_utils.py
robustlink/generate_metacells_rna.py
robustlink/utils.py
robustlink/scf/SCF_main_repeat_subsampling.py
robustlink/scf/SCF_utils.py
robustlink/scf/__init__.py
robustlink/scf/basic_utils.py
robustlink/scf/clst_utils.py
robustlink-0.1.4.dist-info/METADATA
robustlink-0.1.4.dist-info/WHEEL
robustlink-0.1.4.dist-info/licenses/LICENSE
robustlink-0.1.4.dist-info/RECORD
