Metadata-Version: 2.1
Name: robustlink
Version: 0.1.4
Summary: A python package for linking genes and enhancers
Project-URL: Homepage, https://github.com/FangmingXie/robustlink
Author-email: Fangming Xie <f7xie@ucsd.edu>, Ethan Armand <earmand@ucsd.edu>, Eran Mukamel <emukamel@ucsd.edu>
License-File: LICENSE
Classifier: License :: OSI Approved :: MIT License
Classifier: Programming Language :: Python :: 3.8
Requires-Python: >=3.8
